Metadata-Version: 2.1
Name: Mensajes-ALISrj
Version: 6.0
Summary: Un paquete para saludar y despedir
Author: ALISrj
Author-email: alexis.rj2110@gmail.com
Classifier: Environment :: Console
Classifier: License :: OSI Approved :: MIT License
License-File: LICENSE
Requires-Dist: numpy (>=1.23.0)
